oddsapi_ev/__init__.py
oddsapi_ev/ev.py
oddsapi_ev-0.0.1.dist-info/METADATA
oddsapi_ev-0.0.1.dist-info/WHEEL
oddsapi_ev-0.0.1.dist-info/licenses/LICENSE
oddsapi_ev-0.0.1.dist-info/RECORD
