Metadata-Version: 2.1
Name: oddsapi_ev
Version: 0.0.1
Summary: The module gets upcoming sports betting odds from The Odds API and calculates the expected value (ev) of that bet with regard to either or both of two standards of 'true odds'.
Project-URL: Homepage, https://github.com/roman-smith/oddsapi_ev
Author-email: Roman Smith <roman.smith1923@gmail.com>
License: Copyright (c) 2018 The Python Packaging Authority
Classifier: License :: OSI Approved :: MIT License
Classifier: Operating System :: OS Independent
Classifier: Programming Language :: Python :: 3
Requires-Python: >=3.7
